owlapy/__init__.py
owlapy/converter.py
owlapy/iri.py
owlapy/meta_classes.py
owlapy/namespaces.py
owlapy/owl_annotation.py
owlapy/owl_axiom.py
owlapy/owl_data_ranges.py
owlapy/owl_datatype.py
owlapy/owl_hierarchy.py
owlapy/owl_individual.py
owlapy/owl_literal.py
owlapy/owl_object.py
owlapy/owl_ontology.py
owlapy/owl_property.py
owlapy/owl_reasoner.py
owlapy/owlapi_mapper.py
owlapy/parser.py
owlapy/providers.py
owlapy/render.py
owlapy/static_funcs.py
owlapy/swrl.py
owlapy/util_owl_static_funcs.py
owlapy/utils.py
owlapy/vocab.py
owlapy/abstracts/__init__.py
owlapy/abstracts/abstract_owl_ontology.py
owlapy/abstracts/abstract_owl_reasoner.py
owlapy/class_expression/__init__.py
owlapy/class_expression/class_expression.py
owlapy/class_expression/nary_boolean_expression.py
owlapy/class_expression/owl_class.py
owlapy/class_expression/restriction.py
owlapy/entities/__init__.py
owlapy/jar_dependencies/RoaringBitmap-0.6.32.jar
owlapy/jar_dependencies/automaton-1.11-8.jar
owlapy/jar_dependencies/caffeine-2.6.1.jar
owlapy/jar_dependencies/commons-io-2.5.jar
owlapy/jar_dependencies/commons-rdf-api-0.5.0.jar
owlapy/jar_dependencies/elk-owl-implementation-0.6.0.jar
owlapy/jar_dependencies/elk-owl-model-0.6.0.jar
owlapy/jar_dependencies/elk-owlapi-0.6.0.jar
owlapy/jar_dependencies/elk-reasoner-0.6.0.jar
owlapy/jar_dependencies/elk-util-collections-0.6.0.jar
owlapy/jar_dependencies/elk-util-common-0.6.0.jar
owlapy/jar_dependencies/elk-util-concurrent-0.6.0.jar
owlapy/jar_dependencies/elk-util-hashing-0.6.0.jar
owlapy/jar_dependencies/elk-util-logging-0.6.0.jar
owlapy/jar_dependencies/guava-22.0.jar
owlapy/jar_dependencies/hppcrt-0.7.5.jar
owlapy/jar_dependencies/javax.inject-1.jar
owlapy/jar_dependencies/jaxb-api-2.3.1.jar
owlapy/jar_dependencies/jcl-over-slf4j-1.7.22.jar
owlapy/jar_dependencies/jfact-5.0.3.jar
owlapy/jar_dependencies/jgrapht-core-1.2.0.jar
owlapy/jar_dependencies/openllet-core-2.6.5.jar
owlapy/jar_dependencies/openllet-functions-2.6.5.jar
owlapy-1.6.2.dist-info/LICENSE
owlapy-1.6.2.dist-info/METADATA
owlapy-1.6.2.dist-info/WHEEL
owlapy-1.6.2.dist-info/entry_points.txt
owlapy-1.6.2.dist-info/top_level.txt
owlapy-1.6.2.dist-info/RECORD
