Metadata-Version: 2.1
Name: owlapy
Version: 1.6.2
Summary: OWLAPY is a Python Framework for creating and manipulating OWL Ontologies.
Home-page: https://github.com/dice-group/owlapy
Author: Caglar Demir
Author-email: caglardemir8@gmail.com
Classifier: Programming Language :: Python :: 3.10
Classifier: License :: OSI Approved :: MIT License
Classifier: Topic :: Scientific/Engineering
Requires-Python: >=3.10.13
License-File: LICENSE
Requires-Dist: scikit-learn >=1.5.2
Requires-Dist: pandas >=1.5.0
Requires-Dist: requests >=2.32.3
Requires-Dist: rdflib >=6.0.2
Requires-Dist: parsimonious >=0.8.1
Requires-Dist: sortedcontainers >=2.4.0
Requires-Dist: owlready2 >=0.40
Requires-Dist: JPype1 >=1.5.0
Requires-Dist: tqdm >=4.66.5
Requires-Dist: fastapi >=0.115.5
Requires-Dist: httpx >=0.27.2
Requires-Dist: uvicorn >=0.32.1
Requires-Dist: dicee ==0.2.0
Requires-Dist: litserve >=0.2.0
Requires-Dist: dspy ==3.0.3
Provides-Extra: dev
Requires-Dist: scikit-learn >=1.5.2 ; extra == 'dev'
Requires-Dist: pandas >=1.5.0 ; extra == 'dev'
Requires-Dist: requests >=2.32.3 ; extra == 'dev'
Requires-Dist: rdflib >=6.0.2 ; extra == 'dev'
Requires-Dist: parsimonious >=0.8.1 ; extra == 'dev'
Requires-Dist: sortedcontainers >=2.4.0 ; extra == 'dev'
Requires-Dist: owlready2 >=0.40 ; extra == 'dev'
Requires-Dist: JPype1 >=1.5.0 ; extra == 'dev'
Requires-Dist: tqdm >=4.66.5 ; extra == 'dev'
Requires-Dist: fastapi >=0.115.5 ; extra == 'dev'
Requires-Dist: httpx >=0.27.2 ; extra == 'dev'
Requires-Dist: uvicorn >=0.32.1 ; extra == 'dev'
Requires-Dist: dicee ==0.2.0 ; extra == 'dev'
Requires-Dist: litserve >=0.2.0 ; extra == 'dev'
Requires-Dist: dspy ==3.0.3 ; extra == 'dev'
Requires-Dist: pytest >=8.1.1 ; extra == 'dev'
Requires-Dist: ruff >=0.7.2 ; extra == 'dev'
Provides-Extra: min
Requires-Dist: scikit-learn >=1.5.2 ; extra == 'min'
Requires-Dist: pandas >=1.5.0 ; extra == 'min'
Requires-Dist: requests >=2.32.3 ; extra == 'min'
Requires-Dist: rdflib >=6.0.2 ; extra == 'min'
Requires-Dist: parsimonious >=0.8.1 ; extra == 'min'
Requires-Dist: sortedcontainers >=2.4.0 ; extra == 'min'
Requires-Dist: owlready2 >=0.40 ; extra == 'min'
Requires-Dist: JPype1 >=1.5.0 ; extra == 'min'
Requires-Dist: tqdm >=4.66.5 ; extra == 'min'
Requires-Dist: fastapi >=0.115.5 ; extra == 'min'
Requires-Dist: httpx >=0.27.2 ; extra == 'min'
Requires-Dist: uvicorn >=0.32.1 ; extra == 'min'
Requires-Dist: dicee ==0.2.0 ; extra == 'min'
Requires-Dist: litserve >=0.2.0 ; extra == 'min'
Requires-Dist: dspy ==3.0.3 ; extra == 'min'
